LICENSE
MANIFEST.in
README.rst
setup.py
test_community.py
bin/community
community/__init__.py
community/community_louvain.py
community/community_status.py
docs/Makefile
docs/api.rst
docs/conf.py
docs/index.rst
docs/_static/default.css
docs/_templates/layout.html
python_louvain.egg-info/PKG-INFO
python_louvain.egg-info/SOURCES.txt
python_louvain.egg-info/dependency_links.txt
python_louvain.egg-info/requires.txt
python_louvain.egg-info/top_level.txt