Metadata-Version: 1.1
Name: python-louvain
Version: 0.12
Summary: Louvain algorithm for community detection
Home-page: https://github.com/taynaud/python-louvain
Author: Thomas Aynaud
Author-email: taynaud@gmail.com
License: BSD
Platform: UNKNOWN
Classifier: Programming Language :: Python
Classifier: Programming Language :: Python :: 2.7
Classifier: Programming Language :: Python :: 3
Classifier: License :: OSI Approved :: BSD License
Classifier: Development Status :: 4 - Beta
